agentensemble/__init__.py
agentensemble/py.typed
agentensemble/agents/__init__.py
agentensemble/agents/base.py
agentensemble/agents/hybrid_agent.py
agentensemble/agents/rag_agent.py
agentensemble/agents/react_agent.py
agentensemble/agents/stategraph_agent.py
agentensemble/agents/structured_agent.py
agentensemble/orchestration/__init__.py
agentensemble/orchestration/ensemble.py
agentensemble/orchestration/pipeline.py
agentensemble/orchestration/supervisor.py
agentensemble/orchestration/swarm.py
agentensemble/testing/__init__.py
agentensemble/testing/benchmark.py
agentensemble/testing/comparison.py
agentensemble/testing/metrics.py
agentensemble/tools/__init__.py
agentensemble/tools/rag.py
agentensemble/tools/registry.py
agentensemble/tools/scraper.py
agentensemble/tools/search.py
agentensemble/tools/validator.py
agentensemble/utils/__init__.py
agentensemble/utils/llm.py
agentensemble-0.1.0.dist-info/METADATA
agentensemble-0.1.0.dist-info/WHEEL
agentensemble-0.1.0.dist-info/top_level.txt
agentensemble-0.1.0.dist-info/RECORD
