Metadata-Version: 2.4
Name: agentensemble
Version: 0.1.0
Summary: Orchestrate AI agents in perfect harmony - A comprehensive Python framework for building, testing, and orchestrating multi-agent AI systems
Author-email: Irfan Ali <irfanali29@hotmail.com>
Maintainer-email: Irfan Ali <irfanali29@hotmail.com>
License: MIT
Project-URL: Homepage, https://github.com/irfanalidv/AgentEnsemble
Project-URL: Documentation, https://github.com/irfanalidv/AgentEnsemble#readme
Project-URL: Repository, https://github.com/irfanalidv/AgentEnsemble
Project-URL: Issues, https://github.com/irfanalidv/AgentEnsemble/issues
Keywords: ai-agents,multi-agent,orchestration,langgraph,langchain,rag,agent-testing,agentic-ai,state-graph,react-agent
Classifier: Development Status :: 3 - Alpha
Classifier: Intended Audience :: Developers
Classifier: Topic :: Scientific/Engineering :: Artificial Intelligence
Classifier: License :: OSI Approved :: MIT License
Classifier: Programming Language :: Python :: 3
Classifier: Programming Language :: Python :: 3.9
Classifier: Programming Language :: Python :: 3.10
Classifier: Programming Language :: Python :: 3.11
Classifier: Programming Language :: Python :: 3.12
Requires-Python: >=3.9
Requires-Dist: langchain>=0.1.0
Requires-Dist: langchain-core>=0.1.0
Requires-Dist: langchain-community>=0.0.20
Requires-Dist: langchain-mistralai>=0.1.0
Requires-Dist: langgraph>=0.0.20
Requires-Dist: pydantic>=2.0.0
Requires-Dist: typing-extensions>=4.5.0
Requires-Dist: python-dotenv>=1.0.0
Provides-Extra: dev
Requires-Dist: pytest>=7.0.0; extra == "dev"
Requires-Dist: pytest-asyncio>=0.21.0; extra == "dev"
Requires-Dist: black>=23.0.0; extra == "dev"
Requires-Dist: ruff>=0.1.0; extra == "dev"
Requires-Dist: mypy>=1.0.0; extra == "dev"
Requires-Dist: pytest-cov>=4.0.0; extra == "dev"
Provides-Extra: observability
Requires-Dist: langsmith>=0.1.0; extra == "observability"
Requires-Dist: opentelemetry-api>=1.20.0; extra == "observability"
Provides-Extra: rag
Requires-Dist: chromadb>=0.4.0; extra == "rag"
Requires-Dist: sentence-transformers>=2.2.0; extra == "rag"
Requires-Dist: langchain-text-splitters>=0.0.1; extra == "rag"
Requires-Dist: beautifulsoup4>=4.12.0; extra == "rag"
Requires-Dist: langchain-mistralai>=0.1.0; extra == "rag"
Provides-Extra: search
Requires-Dist: duckduckgo-search>=4.0.0; extra == "search"
Requires-Dist: google-search-results>=2.4.2; extra == "search"
Provides-Extra: all
Requires-Dist: agentensemble[dev,observability,rag,search]; extra == "all"
